bystro-2.0.0.dist-info/METADATA
bystro-2.0.0.dist-info/WHEEL
bystro-2.0.0.dist-info/entry_points.txt
bystro/stochastic_gradient_langevin/tests/test_sgld_pt.py
bystro/stochastic_gradient_langevin/tests/__init__.py
bystro/stochastic_gradient_langevin/__init__.py
bystro/stochastic_gradient_langevin/sgld_optimizer_pt.py
bystro/stochastic_gradient_langevin/sgld_scheduler.py
bystro/_template_sgd_np.py
bystro/rare_variant/tests/test_reduced_rank.py
bystro/rare_variant/tests/__init__.py
bystro/rare_variant/tests/test_mrf.py
bystro/rare_variant/__init__.py
bystro/rare_variant/_base_mrf.py
bystro/rare_variant/markov_random_field_nce.py
bystro/rare_variant/reduced_rank.py
bystro/__init__.py
bystro/utils/timer.py
bystro/utils/tests/test_timer.py
bystro/utils/tests/test_compress.py
bystro/utils/__init__.py
bystro/utils/.hypothesis/unicode_data/13.0.0/charmap.json.gz
bystro/utils/.hypothesis/unicode_data/13.0.0/codec-utf-8.json.gz
bystro/utils/compress.py
bystro/utils/covariates.py
bystro/covariance/losses_covariances.py
bystro/covariance/covariance_cov_shrinkage.py
bystro/covariance/positive_definite_average.py
bystro/covariance/_base_precision.py
bystro/covariance/tests/test_base_covariance.py
bystro/covariance/tests/test_operator_shrinkage.py
bystro/covariance/tests/test_covariance_np.py
bystro/covariance/tests/test_test.py
bystro/covariance/tests/test_optimal_shrinkage.py
bystro/covariance/tests/test_geodesics.py
bystro/covariance/tests/__init__.py
bystro/covariance/tests/test_hypothesis_classical.py
bystro/covariance/tests/test_cov_shrinkage.py
bystro/covariance/tests/test_hypothesis_hd.py
bystro/covariance/tests/test_base_precision.py
bystro/covariance/tests/hypothesis_hd_data.pkl
bystro/covariance/tests/test_losses_covariances.py
bystro/covariance/tests/test_positive_definite_average.py
bystro/covariance/__init__.py
bystro/covariance/test.py
bystro/covariance/_precision_np.py
bystro/covariance/hypothesis_hd.py
bystro/covariance/_base_covariance.py
bystro/covariance/opt_shrink.py
bystro/covariance/_covariance_np.py
bystro/covariance/geodesics.py
bystro-2.0.0.dist-info/RECORD
