Metadata-Version: 2.3
Name: bystro
Version: 2.0.0
Classifier: Programming Language :: Rust
Classifier: Programming Language :: Python :: Implementation :: CPython
Classifier: Programming Language :: Python :: Implementation :: PyPy
Requires-Dist: openpyxl ==3.1.2
Requires-Dist: boto3 ==1.28.9
Requires-Dist: liftover ==1.2.2
Requires-Dist: msgspec ==0.18.6
Requires-Dist: numba ==0.60.0
Requires-Dist: opensearch-py[async] ==2.5.0
Requires-Dist: numpy ==1.26.4
Requires-Dist: pandas ==2.2.2
Requires-Dist: pyarrow ==16.1.0
Requires-Dist: pystalk ==0.7.0
Requires-Dist: ruamel-yaml ==0.17.31
Requires-Dist: scikit-allel ==1.3.8
Requires-Dist: scikit-learn ==1.5.1
Requires-Dist: skops ==0.7.post0
Requires-Dist: tqdm ==4.66.3
Requires-Dist: cloudpickle ==3.0.0
Requires-Dist: torch ==2.2
Requires-Dist: psutil ==5.9.6
Requires-Dist: matplotlib ==3.7.1
Requires-Dist: ecos ==2.0.13
Requires-Dist: osqp ==0.6.5
Requires-Dist: cvxpy ==1.5.2
Requires-Dist: pyro-ppl ==1.9.1
Requires-Dist: somadata ==1.0.0
Requires-Dist: statsmodels ==0.14.2
Requires-Dist: nest-asyncio ==1.6.0
Requires-Python: >=3.11.0, <3.13.0
